odc/algo/__init__.py
odc/algo/_broadcast.py
odc/algo/_dask.py
odc/algo/_dask_stream.py
odc/algo/_geomedian.py
odc/algo/_masking.py
odc/algo/_memsink.py
odc/algo/_numeric.py
odc/algo/_numexpr.py
odc/algo/_percentile.py
odc/algo/_rgba.py
odc/algo/_tiff.py
odc/algo/_tools.py
odc/algo/_types.py
odc/algo/_warp.py
odc/algo/pixel.py
odc_algo-1.1.1.dist-info/licenses/LICENSE
odc_algo-1.1.1.dist-info/METADATA
odc_algo-1.1.1.dist-info/WHEEL
odc_algo-1.1.1.dist-info/top_level.txt
odc_algo-1.1.1.dist-info/RECORD
