Metadata-Version: 2.4
Name: odc-algo
Version: 1.1.1
Summary: Miscellaneous Algorithmic helper methods
Author: Open Data Cube
Maintainer: Open Data Cube
License-Expression: Apache-2.0
Project-URL: Homepage, https://opendatacube.org/
Project-URL: Source, https://github.com/opendatacube/odc-algo/
Requires-Python: >=3.10
License-File: LICENSE
Requires-Dist: affine
Requires-Dist: dask
Requires-Dist: dask-image
Requires-Dist: distributed
Requires-Dist: geomad
Requires-Dist: numexpr
Requires-Dist: numpy
Requires-Dist: rasterio>=1.3.2
Requires-Dist: odc-geo
Requires-Dist: scikit-image
Requires-Dist: toolz
Requires-Dist: xarray
Provides-Extra: s3
Requires-Dist: boto3; extra == "s3"
Requires-Dist: odc-cloud; extra == "s3"
Dynamic: license-file
